Metadata-Version: 2.1
Name: prodamuspy
Version: 1.0.2
Summary: Prodamus hash verifier
Home-page: https://github.com/dnagikh/python-prodamus
Maintainer: Daniil Nagikh
Maintainer-email: dnagikh@gmail.com
License: LICENSE.md
Keywords: prodamus,hash,hmac,verify,sign
Classifier: Programming Language :: Python
Classifier: Development Status :: 4 - Beta
Classifier: Environment :: Plugins
Classifier: Intended Audience :: Developers
Classifier: License :: OSI Approved :: MIT License
Classifier: Operating System :: OS Independent
Classifier: Topic :: Software Development :: Libraries :: Python Modules
Classifier: Topic :: Security :: Cryptography
License-File: LICENSE.md
